pandas_scd.py
pandas_scd2-1.0.3.dist-info/METADATA
pandas_scd2-1.0.3.dist-info/WHEEL
pandas_scd2-1.0.3.dist-info/top_level.txt
pandas_scd2-1.0.3.dist-info/RECORD
