Metadata-Version: 2.1
Name: pandas-scd2
Version: 1.0.3
Summary: slowly changing dimension with pandas
Home-page: https://gitlab.com/liranc/pandas_scd
Keywords: scd,slowly changing dimension,pandas
Requires-Python: >=3.8
Requires-Dist: pandas
Requires-Dist: tabulate
Requires-Dist: duckdb
